ministatus/__init__.py
ministatus/__main__.py
ministatus/appdirs.py
ministatus/bot/__init__.py
ministatus/bot/bot.py
ministatus/bot/cogs/__init__.py
ministatus/bot/cogs/cleanup.py
ministatus/bot/cogs/errors.py
ministatus/bot/cogs/owner.py
ministatus/bot/cogs/status/__init__.py
ministatus/bot/cogs/status/alert.py
ministatus/bot/cogs/status/cog.py
ministatus/bot/cogs/status/graph.py
ministatus/bot/cogs/status/permissions.py
ministatus/bot/cogs/status/query.py
ministatus/bot/cogs/status/views/__init__.py
ministatus/bot/cogs/status/views/alert.py
ministatus/bot/cogs/status/views/book.py
ministatus/bot/cogs/status/views/display.py
ministatus/bot/cogs/status/views/overview.py
ministatus/bot/cogs/status/views/query.py
ministatus/bot/cogs/status/views/summary.py
ministatus/bot/db.py
ministatus/bot/dt.py
ministatus/bot/errors.py
ministatus/bot/views.py
ministatus/cli/__init__.py
ministatus/cli/__main__.py
ministatus/cli/commands/__init__.py
ministatus/cli/commands/appdirs.py
ministatus/cli/commands/config.py
ministatus/cli/commands/db.py
ministatus/cli/commands/debug.py
ministatus/cli/commands/invite.py
ministatus/cli/commands/markers.py
ministatus/cli/commands/start.py
ministatus/db/__init__.py
ministatus/db/client.py
ministatus/db/connection.py
ministatus/db/converters.py
ministatus/db/errors.py
ministatus/db/migrations/001-base.sql
ministatus/db/migrations/002-status.sql
ministatus/db/migrations/003-num-players.sql
ministatus/db/migrations/004-status-details.sql
ministatus/db/migrations/005-downtime.sql
ministatus/db/migrations.py
ministatus/db/models.py
ministatus/db/secret.py
ministatus/logging.py
ministatus/py.typed
ministatus/state.py
ministatus-1.0.5.dist-info/licenses/LICENSE
ministatus-1.0.5.dist-info/WHEEL
ministatus-1.0.5.dist-info/entry_points.txt
ministatus-1.0.5.dist-info/METADATA
ministatus-1.0.5.dist-info/RECORD
