Metadata-Version: 2.4
Name: ministatus
Version: 1.0.5
Summary: A Discord bot for managing game server status embeds.
Author: thegamecracks
License-Expression: MIT
License-File: LICENSE
Classifier: Development Status :: 5 - Production/Stable
Classifier: Environment :: Console
Classifier: Intended Audience :: End Users/Desktop
Classifier: Operating System :: OS Independent
Classifier: Programming Language :: Python
Classifier: Programming Language :: Python :: 3
Classifier: Programming Language :: Python :: 3 :: Only
Classifier: Programming Language :: Python :: 3.11
Classifier: Programming Language :: Python :: 3.12
Classifier: Programming Language :: Python :: 3.13
Classifier: Programming Language :: Python :: 3.14
Classifier: Programming Language :: SQL
Classifier: Topic :: Communications
Classifier: Topic :: Communications :: Chat
Classifier: Topic :: Internet
Classifier: Topic :: Internet :: Name Service (DNS)
Classifier: Typing :: Typed
Requires-Dist: asqlite~=2.0
Requires-Dist: click~=8.3
Requires-Dist: discord-py~=2.6
Requires-Dist: dnspython~=2.8
Requires-Dist: ipaddress~=1.0
Requires-Dist: little-a2s~=0.7.1
Requires-Dist: matplotlib~=3.10
Requires-Dist: opengsq~=3.6
Requires-Dist: platformdirs~=4.5
Requires-Dist: pydantic~=2.12
Requires-Python: >=3.11
Project-URL: Homepage, https://github.com/thegamecracks/ministatus
Project-URL: GitHub, https://github.com/thegamecracks/ministatus
Project-URL: Issues, https://github.com/thegamecracks/ministatus/issues
